mp3/rainbow/game_of_life.sv
module game_of_life (
    input  logic clk,                 
    input  logic update,               
    input  logic [63:0] current_bits, // 1 bit per cell: 1 = alive, 0 = dead
    output logic [63:0] next_bits     // 1 bit per cell for next generation
);

    localparam int ROWS = 8;  
    localparam int COLS = 8;  

    // internal loop variables
    int y, x;                
    int delta_y, delta_x;    // offsets for neighbor scanning (-1, 0, 1)
    int neighbor_row, neighbor_col; // coordinates of neighbor
    int cell_index, neighbor_index; 
    int live_neighbors;      // count of live neighbors 

    always_ff @(posedge clk) begin
        if (update) begin
            for (y = 0; y < ROWS; y = y + 1) begin
                for (x = 0; x < COLS; x = x + 1) begin
                    cell_index = y * COLS + x; // convert coordinates
                    live_neighbors = 0;

                    // scan for all 8 neighbors
                    for (delta_y = -1; delta_y <= 1; delta_y = delta_y + 1) begin
                        for (delta_x = -1; delta_x <= 1; delta_x = delta_x + 1) begin
                            if (!(delta_y == 0 && delta_x == 0)) begin
                                // wrap around edges (toroidal grid)
                                neighbor_row = (y + delta_y + ROWS) % ROWS;
                                neighbor_col = (x + delta_x + COLS) % COLS;
                                neighbor_index = neighbor_row * COLS + neighbor_col;
                                // add 1 if neighbor is alive
                                live_neighbors += current_bits[neighbor_index];
                            end
                        end
                    end

                    // apply rules
                    next_bits[cell_index] <= (live_neighbors == 3) || 
                                             (current_bits[cell_index] && live_neighbors == 2);
                end
            end
        end
    end

endmodule

mp3/rainbow/game_of_life_tb.sv
`timescale 1ns/1ps
`include "game_of_life.sv"

module game_of_life_tb;

    logic clk = 0;
    logic update = 0;

    logic [63:0] current_bits;
    logic [63:0] next_bits;

    game_of_life dut (
        .clk(clk),
        .update(update),
        .current_bits(current_bits),
        .next_bits(next_bits)
    );

    always #5 clk = ~clk;

    initial begin
        $dumpfile("game_of_life.vcd");
        $dumpvars(0, game_of_life_tb);

        current_bits = 64'b0;
        current_bits[34] = 1'b1; // (4,2)
        current_bits[35] = 1'b1; // (4,3)
        current_bits[36] = 1'b1; // (4,4)

        // loop over 4 generations
        repeat (4) begin
            #10; update = 1;
            #10; update = 0;

            // wait for next_bits to settle
            #10;

            // apply next state -> current_bits
            current_bits = next_bits;
        end

        $finish;
    end

endmodule

mp3/game_of_life.vcd
$date
	Wed Oct 29 23:06:08 2025
$end
$version
	Icarus Verilog
$end
$timescale
	1ps
$end
$scope module game_of_life_tb $end
$var wire 64 ! next_bits [63:0] $end
$var reg 1 " clk $end
$var reg 64 # current_bits [63:0] $end
$var reg 1 $ update $end
$scope module dut $end
$var wire 1 " clk $end
$var wire 64 % current_bits [63:0] $end
$var wire 1 $ update $end
$var reg 64 & next_bits [63:0] $end
$var integer 32 ' cell_index [31:0] $end
$var integer 32 ( delta_x [31:0] $end
$var integer 32 ) delta_y [31:0] $end
$var integer 32 * live_neighbors [31:0] $end
$var integer 32 + neighbor_col [31:0] $end
$var integer 32 , neighbor_index [31:0] $end
$var integer 32 - neighbor_row [31:0] $end
$var integer 32 . x [31:0] $end
$var integer 32 / y [31:0] $end
$upscope $end
$upscope $end
$enddefinitions $end
#0
$dumpvars
b0 /
b0 .
b0 -
b0 ,
b0 +
b0 *
b0 )
b0 (
b0 '
bx &
b1110000000000000000000000000000000000 %
0$
b1110000000000000000000000000000000000 #
0"
bx !
$end
#5000
1"
#10000
0"
1$
#15000
b10000000100000001000000000000000000000000000 !
b10000000100000001000000000000000000000000000 &
b0 *
b1000 /
b111111 '
b1000 .
b0 ,
b0 +
b0 -
b10 (
b10 )
1"
#20000
0"
0$
#25000
1"
#30000
0"
b10000000100000001000000000000000000000000000 #
b10000000100000001000000000000000000000000000 %
#35000
1"
#40000
0"
1$
#45000
b1110000000000000000000000000000000000 !
b1110000000000000000000000000000000000 &
b0 *
b0 ,
b0 +
b0 -
b10 (
b10 )
b111111 '
b1000 .
b1000 /
1"
#50000
0"
0$
#55000
1"
#60000
0"
b1110000000000000000000000000000000000 #
b1110000000000000000000000000000000000 %
#65000
1"
#70000
0"
1$
#75000
b10000000100000001000000000000000000000000000 !
b10000000100000001000000000000000000000000000 &
b0 *
b0 ,
b0 +
b0 -
b10 (
b10 )
b111111 '
b1000 .
b1000 /
1"
#80000
0"
0$
#85000
1"
#90000
0"
b10000000100000001000000000000000000000000000 #
b10000000100000001000000000000000000000000000 %
#95000
1"
#100000
0"
1$
#105000
b1110000000000000000000000000000000000 !
b1110000000000000000000000000000000000 &
b0 *
b0 ,
b0 +
b0 -
b10 (
b10 )
b111111 '
b1000 .
b1000 /
1"
#110000
0"
0$
#115000
1"
#120000
0"
b1110000000000000000000000000000000000 #
b1110000000000000000000000000000000000 %
